rstnpy/__init__.py
rstnpy/exceptions.py
rstnpy/rstn.py
rstnpy/rstndownloader.py
rstnpy/rstnfile.py
rstnpy-1.1.dist-info/LICENSE
rstnpy-1.1.dist-info/METADATA
rstnpy-1.1.dist-info/WHEEL
rstnpy-1.1.dist-info/top_level.txt
rstnpy-1.1.dist-info/RECORD
