Metadata-Version: 2.1
Name: rstnpy
Version: 1.1
Summary: Library used to work with rstn-1-second data
Home-page: https://github.com/craam/rstnpy
Author: Edison Neto
Author-email: ednetoali@gmail.com
License: UNKNOWN
Platform: UNKNOWN
Classifier: Programming Language :: Python :: 3.5
Classifier: Programming Language :: Python :: 3.6
Classifier: Programming Language :: Python :: 3.7
Classifier: License :: OSI Approved :: GNU General Public License v2 (GPLv2)
Classifier: Operating System :: OS Independent
Requires-Dist: requests (>=2.20)
Requires-Dist: numpy (>=1.13)
Requires-Dist: pandas (>=0.21matplotlib>=2.2.2)
